{
  "questions": [
    {
      "id": "1",
      "title": "Which of the following tags is used to define a hyperlink in HTML ?",
      "correctAnswer": "<a>",
      "options": [
        "a",
        "link",
        "herf",
        "link"
      ],
      "level": "easy"
    },
    {
      "id": "2",
      "title": "What does the 'href' attribute define in an HTML <a> tag",
      "correctAnswer": "Hypertext reference",
      "options": [
        "Header reference",
        "Hyperlink reference",
        "Hypertext reference",
        "Hierarchy reference"
      ],
      "level": "medium"
    },
    {
      "id": "3",
      "title": "What is my name ?",
      "correctAnswer": "Prazol",
      "options": [
        "Prazol",
        "Bara",
        "Upreti",
        "Kc"
      ],
      "level": "hard"
    },
    {
      "id": "4",
      "title": "What is https",
      "correctAnswer": "protocol",
      "options": [
        "keyword",
        "protocol",
        "name",
        "term"
      ],
      "level": "hard"
    },
    {
      "id": "5",
      "title": "who is barakoti gf?",
      "correctAnswer": "leah",
      "options": [
        "leah",
        "sudip",
        "kalyan",
        "dhakal"
      ],
      "level": "easy"
    }
  ]
}